sgptools/__init__.py
sgptools/methods.py
sgptools/objectives.py
sgptools/core/__init__.py
sgptools/core/augmented_gpr.py
sgptools/core/augmented_sgpr.py
sgptools/core/osgpr.py
sgptools/core/transformations.py
sgptools/kernels/__init__.py
sgptools/kernels/attentive.py
sgptools/kernels/neural_network.py
sgptools/kernels/neural_spectral.py
sgptools/utils/__init__.py
sgptools/utils/data.py
sgptools/utils/gpflow.py
sgptools/utils/metrics.py
sgptools/utils/misc.py
sgptools/utils/tsp.py
sgptools-2.0.4.dist-info/licenses/LICENSE.txt
sgptools-2.0.4.dist-info/METADATA
sgptools-2.0.4.dist-info/WHEEL
sgptools-2.0.4.dist-info/top_level.txt
sgptools-2.0.4.dist-info/RECORD
