Metadata-Version: 2.4
Name: sgptools
Version: 2.0.4
Summary: A Python library for efficient sensor placement and informative path planning
Home-page: https://www.SGP-Tools.com
Author: Kalvik
Author-email: itskalvik@gmail.com
License: Apache-2.0
Classifier: Programming Language :: Python :: 3
Classifier: License :: OSI Approved :: Apache Software License
Classifier: Operating System :: OS Independent
Requires-Python: >=3.6
License-File: LICENSE.txt
Requires-Dist: apricot-select
Requires-Dist: matplotlib
Requires-Dist: pandas
Requires-Dist: scikit-learn
Requires-Dist: scipy
Requires-Dist: numpy<2.0.0
Requires-Dist: ortools
Requires-Dist: scikit-image
Requires-Dist: shapely
Requires-Dist: cma
Requires-Dist: bayesian-optimization
Requires-Dist: hkb_diamondsquare
Requires-Dist: tensorflow-probability[tf]>=0.21.0
Requires-Dist: tensorflow>=2.13.0; platform_machine != "arm64"
Requires-Dist: tensorflow-aarch64>=2.13.0; platform_machine == "arm64"
Requires-Dist: tensorflow-macos>=2.13.0; platform_system == "Darwin" and platform_machine == "arm64"
Requires-Dist: typing_extensions
Requires-Dist: gpflow>=2.7.0
Requires-Dist: pillow
Requires-Dist: geopandas
Dynamic: author
Dynamic: author-email
Dynamic: classifier
Dynamic: description
Dynamic: description-content-type
Dynamic: home-page
Dynamic: license
Dynamic: license-file
Dynamic: requires-dist
Dynamic: requires-python
Dynamic: summary
